suitcase/nomad_camels_hdf5/__init__.py
suitcase/nomad_camels_hdf5/_version.py
suitcase/nomad_camels_hdf5/tests/__init__.py
suitcase/nomad_camels_hdf5/tests/conftest.py
suitcase/nomad_camels_hdf5/tests/tests.py
suitcase_nomad_camels_hdf5-1.3.1.dist-info/licenses/LICENSE
suitcase_nomad_camels_hdf5-1.3.1.dist-info/METADATA
suitcase_nomad_camels_hdf5-1.3.1.dist-info/WHEEL
suitcase_nomad_camels_hdf5-1.3.1.dist-info/top_level.txt
suitcase_nomad_camels_hdf5-1.3.1.dist-info/RECORD
