Metadata-Version: 2.4
Name: suitcase-nomad-camels-hdf5
Version: 1.3.1
License: BSD (3-clause)
Classifier: Development Status :: 2 - Pre-Alpha
Classifier: Natural Language :: English
Classifier: Programming Language :: Python :: 3.6
Requires-Python: >=3.6
License-File: LICENSE
Requires-Dist: event-model>=1.8.0
Requires-Dist: suitcase-utils
Requires-Dist: h5py>=3.7.0
Requires-Dist: databroker>=1.2.5
Requires-Dist: bluesky>=1.8.3
Requires-Dist: ophyd>=1.6.4
Requires-Dist: PySide6>=6.5.1
Requires-Dist: numexpr
Dynamic: classifier
Dynamic: description
Dynamic: description-content-type
Dynamic: license
Dynamic: license-file
Dynamic: requires-dist
Dynamic: requires-python
